media_filesize_estimator/__init__.py
media_filesize_estimator/__main__.py
media_filesize_estimator/mediaEstimation.py
media_filesize_estimator/mediaExtraction.py
media_filesize_estimator-1.0.0.dist-info/entry_points.txt
media_filesize_estimator-1.0.0.dist-info/LICENSE
media_filesize_estimator-1.0.0.dist-info/WHEEL
media_filesize_estimator-1.0.0.dist-info/METADATA
media_filesize_estimator-1.0.0.dist-info/RECORD
