Metadata-Version: 2.1
Name: media-filesize-estimator
Version: 1.0.0
Summary: Estimates media file size in different formats w/o actually converting the file
Home-page: https://github.com/kHarshit/media-filesize-estimator
License: MIT
Author: kHarshit
Author-email: kumar_harshit@outlook.com
Requires-Python: >=3.8,<4.0
Classifier: Development Status :: 5 - Production/Stable
Classifier: Intended Audience :: Developers
Classifier: License :: OSI Approved :: MIT License
Classifier: Operating System :: OS Independent
Classifier: Programming Language :: Python :: 3
Classifier: Programming Language :: Python :: 3.10
Classifier: Programming Language :: Python :: 3.8
Classifier: Programming Language :: Python :: 3.9
Classifier: Topic :: Software Development :: Libraries :: Python Modules
Requires-Dist: defusedxml (>=0.7.1,<0.8.0)
Requires-Dist: matplotlib (>=3.5.3,<4.0.0)
Requires-Dist: pymediainfo (>=5.1.0,<6.0.0)
Requires-Dist: rich (>=10.14.0,<11.0.0)
Requires-Dist: typer[all] (>=0.4.0,<0.5.0)
Project-URL: Repository, https://github.com/kHarshit/media-filesize-estimator
